kubernetes_explorer/__init__.py
kubernetes_explorer/kubernetes_explorer.py
kubernetes_explorer/kubernetes_graph.py
kubernetes_explorer/kubex.py
kubernetes_explorer/label_matching.py
kubernetes_explorer/utils.py
kubernetes_explorer-1.0.1.dist-info/LICENSE
kubernetes_explorer-1.0.1.dist-info/METADATA
kubernetes_explorer-1.0.1.dist-info/WHEEL
kubernetes_explorer-1.0.1.dist-info/entry_points.txt
kubernetes_explorer-1.0.1.dist-info/top_level.txt
kubernetes_explorer-1.0.1.dist-info/RECORD
