Metadata-Version: 2.1
Name: kubernetes-explorer
Version: 1.0.1
Summary: Kubernetes Explorer lets you create a graph of the objects and dependencies inside your Kubernetes cluster.
Home-page: https://gitlab.com/jdonzallaz/kubernetes-explorer
Author: Jonathan Donzallaz
Author-email: jonathan.donzallaz@gmail.com
License: UNKNOWN
Platform: UNKNOWN
Classifier: Programming Language :: Python :: 3
Classifier: License :: OSI Approved :: MIT License
Classifier: Operating System :: OS Independent
Requires-Python: >=3.6
Requires-Dist: graphviz (>=0.14)
Requires-Dist: kubernetes (>=11.0.0)
Requires-Dist: pyyaml (>=5.3.1)
